<Properties StartupConfiguration="{5B2B8257-89C6-4E60-B278-8C5BE396B46A}|Default">
  <MonoDevelop.Ide.Workbench />
  <MonoDevelop.Ide.Workspace ActiveConfiguration="Debug|iPhoneSimulator" />
  <MonoDevelop.Ide.DebuggingService.Breakpoints>
    <BreakpointStore />
  </MonoDevelop.Ide.DebuggingService.Breakpoints>
  <MonoDevelop.Ide.DebuggingService.PinnedWatches />
  <MonoDevelop.Ide.ItemProperties.GamesCatalogXamarin.Droid PreferredExecutionTarget="Android.Android_Accelerated_Nougat" AndroidDesignerPreferredTheme="Theme.DeviceDefault.NoActionBar.Fullscreen" />
  <MultiItemStartupConfigurations />
  <MonoDevelop.Ide.ItemProperties.GamesCatalogXamarin.iOS PreferredExecutionTarget="MonoDevelop.IPhone.IPhoneSimulatorTarget.DA44BA27-11EB-4AF7-B205-8918566F8A63">
    <MonoDevelop.MacDev.AppleDevelopmentTeam />
  </MonoDevelop.Ide.ItemProperties.GamesCatalogXamarin.iOS>
</Properties>